<?xml version="1.0"?>
<!DOCTYPE hibernate-mapping PUBLIC "-//Hibernate/Hibernate Mapping DTD 3.0//EN"
"http://hibernate.sourceforge.net/hibernate-mapping-3.0.dtd">
<!-- Generated 15 Apr, 2018 6:48:03 PM by Hibernate Tools 3.5.0.Final -->
<hibernate-mapping>
    <class name="com.constructor.Address" table="ADDRESS">
        <id name="id" type="int" access="field">
            <column name="ID" />
            <generator class="assigned" />
        </id>
        <property name="street" type="java.lang.String" access="field">
            <column name="STREET" />
        </property>
        <property name="city" type="java.lang.String" access="field">
            <column name="CITY" />
        </property>
        <property name="state" type="java.lang.String" access="field">
            <column name="STATE" />
        </property>
        <property name="zipcode" type="java.lang.String" access="field">
            <column name="ZIPCODE" />
        </property>
    </class>
</hibernate-mapping>
